{
    "question": "Apa saja\u00a0unsur- unsur dan langkah menulis monolog??",
    "attachments": [],
    "answers": [
        {
            "answer": "unsur intrinsik novel<br>berikut unsur-unsur yg dimaksud<br>1.tema cerita<br>2.tokoh dan penokohan<br>3.setting atau latar<br>4.sudut pandang<br>5.alur<br>6.amanat",
            "attachments": []
        }
    ],
    "related_questions": [
        {
            "slug": "arti-atau-makna-puisi-itu-sampah-atau-apa-karya-aditya-yuda-kenc-597",
            "question": "Arti atau makna puisi itu sampah atau apa? karya aditya yuda kencana",
            "attachments": [],
            "answers": [
                {
                    "answer": "oh yang itu, puisi itu puisi anekdot, disitu mengandung sindiran kepada orang2 yang suka membuang sampah secara sembarangan,,hampir seluruh tmpat di indonesia di penuhi sampah, maka dari itu penulis membuat puisi trsebut karena mrasa prihatin dengan kualitas kebersihan yang ada di Indonesia yang tampak kotor, khususnya di ibukota jakarta,,\u00a0",
                    "attachments": []
                }
            ]
        },
        {
            "slug": "berikan-contoh-bernegosiasi-dalam-kehidupan-sehari-603",
            "question": "Berikan\u00a0contoh\u00a0bernegosiasi\u00a0dalam\u00a0kehidupan\u00a0sehari",
            "attachments": [],
            "answers": [
                {
                    "answer": "seorang ibu bernegosiasi kepada tukang sayur di pasar mengenai harga bahan2 makanan agar mendapat harga yang murah<br>",
                    "attachments": []
                }
            ]
        },
        {
            "slug": "apa-arti-kata-krisis-dan-reaksi-pada-cerita-anekdot-598",
            "question": "Apa arti kata krisis dan reaksi pada cerita anekdot ?",
            "attachments": [],
            "answers": [
                {
                    "answer": "krisis adalah letak suatu kelucuan pada teks anekdot. sedangkan reaksi adalah reaksi sekitar tentang kelucuan pada teks anekdot tersebut.",
                    "attachments": []
                },
                {
                    "answer": "Krisis : Memuat tahapan peristiwa dan cerita mulai memuncak dan hampir menuju ke penyelesaian.<br>Reaksi : Jawaban terhadap permasalahan yang diajukan pada tahap krisis. Ini merupakan inti kritik yang memuat unsur lucu, konyol dan mengesankan.",
                    "attachments": []
                }
            ]
        },
        {
            "slug": "berikan-penjelasan-seandainya-anda-tidak-setuju-bahwa-koda-sama-d-985",
            "question": "berikan penjelasan seandainya anda tidak setuju bahwa koda sama dengan penutup. Pikirkan bahwa penutup menggambarkan situasi yang seimbang dengan situasi pada orientasi !",
            "attachments": [],
            "answers": [
                {
                    "answer": "koda berbeda dengan penutup. jadi koda itu sudah menemukan cara memecahkan permasalahannya. baru kemudian di penutup adah akhir dari permasalahannya. keadaan penutup harus sama dengan orientasi maksudnya keadaan sudah normal kebali seperti semula, tidak seperti keadaan saat di puncak maslah.<br><br>",
                    "attachments": []
                }
            ]
        },
        {
            "slug": "contoh-teks-negoisasi-yang-berisi-25-dialog-533",
            "question": "Contoh teks negoisasi yang berisi 25 dialog?",
            "attachments": [],
            "answers": [
                {
                    "answer": "Noh banyak :v . itung sendiri yahh ::)<br><br><span>\nNegosiasi\nJual Beli Mobil :</span>\n<span>\n<br></span>\n<span>\n<span>Pembeli\u00a0\u00a0\u00a0\u00a0\u00a0\u00a0\u00a0\u00a0\u00a0\u00a0 : Selamat siang pak,</span></span>\n<span>\n<span>Penjual\u00a0\u00a0\u00a0\u00a0\u00a0\u00a0\u00a0\u00a0\u00a0\u00a0\u00a0\u00a0\u00a0\u00a0\u00a0\u00a0\u00a0\u00a0\u00a0\u00a0\u00a0\u00a0\u00a0 : Selamat siang,\nSilahkan Duduk. Dengan Sdr. Midun Bukan ..?</span></span>\n<span>\n<span>Pembeli\u00a0\u00a0\u00a0\u00a0\u00a0\u00a0\u00a0\u00a0\u00a0\u00a0 : Benar pak, Saya Yang menghubungi\nbapak pagi tadi .</span></span>\n<span>\n<span>Penjual\u00a0\u00a0\u00a0\u00a0\u00a0\u00a0\u00a0\u00a0\u00a0\u00a0\u00a0\u00a0\u00a0\u00a0\u00a0\u00a0\u00a0\u00a0\u00a0\u00a0\u00a0\u00a0\u00a0 : Baiklah, Langsung ke inti nya saja, apa\nbenar sdr midun tertarik dengan mobil yang di iklankan di Koran Riau pos itu?</span></span>\n<span>\n<span>Pembeli\u00a0\u00a0\u00a0\u00a0\u00a0\u00a0\u00a0\u00a0\u00a0\u00a0 : Betul pak, dari foto yang ditampilkan di Koran tersebut,\nsaya tertarik ingin memlihat fisik asli mobil tersebut secara dekat, karena\nberdasarkan foto yang saya lihat, kelihatannya mobil bapak masih dalam keadaan\nbersih dan baru.</span></span>\n<span>\n<span>Penjual\u00a0\u00a0\u00a0\u00a0\u00a0\u00a0\u00a0\u00a0\u00a0\u00a0\u00a0\u00a0\u00a0\u00a0\u00a0\u00a0\u00a0\u00a0\u00a0\u00a0\u00a0\u00a0\u00a0 : Ohh itu betul sekali , mobil itu baru saya\nbeli sekitar 2 tahun yang lalu, dan kondisinya sangat bagus sekali, saya\nmenjualnya karena ingin mengganti mobil yang baru.</span></span>\n<span>\n<span>Pembeli\u00a0\u00a0\u00a0\u00a0\u00a0\u00a0\u00a0\u00a0\u00a0\u00a0 : Memangnya mengapa bapak ingin mengganti mobil tersebut?<br>\napakah mobil itu sudah mengalami kerusakan?</span></span>\n<span>\n<span>Penjual \u00a0\u00a0\u00a0\u00a0\u00a0\u00a0\u00a0\u00a0\u00a0\u00a0\u00a0\u00a0\u00a0\u00a0\u00a0\u00a0\u00a0\u00a0\u00a0\u00a0\u00a0\u00a0 : oh tidak\u2026tidak sama sekali, saya menganti\nmobil itu karena mobil itu terlalu kecil untuk saya sekeluarga , jadi saya\ningin mengganti mobil yang lebih besar dari mobil tersebut.</span></span>\n<span>\n<span>Pembeli\u00a0\u00a0\u00a0\u00a0\u00a0\u00a0\u00a0\u00a0\u00a0\u00a0 : OHH begitu,..!! oh ya pak, bisa saya lihat mobil itu\nsekarang?</span></span>\n<span>\n<span>Penjual\u00a0\u00a0\u00a0\u00a0\u00a0\u00a0\u00a0\u00a0\u00a0\u00a0\u00a0\u00a0\u00a0\u00a0\u00a0\u00a0\u00a0\u00a0\u00a0\u00a0\u00a0\u00a0\u00a0 : tentu , tentu.. lewat sini sdr. midun.(\nberjalan menuju garasi mobil )</span></span>\n<span>\n<span>Pembeli \u00a0\u00a0\u00a0\u00a0\u00a0\u00a0\u00a0\u00a0\u00a0 : baik pak..!</span></span>\n<span>\n<span>Pejual \u00a0\u00a0\u00a0\u00a0\u00a0\u00a0\u00a0\u00a0\u00a0\u00a0\u00a0\u00a0 : Nah, ini lah mobil nya, masih bagus bukan?</span></span>\n<span>\n<span>Pembeli\u00a0\u00a0\u00a0\u00a0\u00a0\u00a0\u00a0\u00a0\u00a0\u00a0 : iya pak, persis seperti foto yang terpajang itu ya.dan\nwarnanya masih mengkilat seperti baru.</span></span>\n<span>\n<span>Penjual\u00a0\u00a0\u00a0\u00a0\u00a0\u00a0\u00a0\u00a0\u00a0\u00a0\u00a0\u00a0\u00a0\u00a0\u00a0\u00a0\u00a0\u00a0\u00a0\u00a0\u00a0\u00a0\u00a0 : Tentu saja, karena mobil ini selalu\nterawatt oleh saya, satu butir debu pun tidak akan saya biarkan menyentuh mobil\nini ( tersenyum simpul )</span></span>\n<span>\n<span>Pembeli\u00a0\u00a0\u00a0\u00a0\u00a0\u00a0\u00a0\u00a0\u00a0\u00a0 : Wah bagus tu pak, kalau boleh tahu, mobil ini rakitan\ntahun berapa pak?</span></span>\n<span>\n<span>Penjual\u00a0\u00a0\u00a0\u00a0\u00a0\u00a0\u00a0\u00a0\u00a0\u00a0\u00a0\u00a0\u00a0\u00a0\u00a0\u00a0\u00a0\u00a0\u00a0\u00a0\u00a0\u00a0\u00a0 : mobil ini tahun 2006. Dan sampai saat ini\nkondisi mesin nya masih seperti baru, itu karena saya rutin servis setiap\nbulannya.</span></span>\n<span>\n<span>Pembeli\u00a0\u00a0\u00a0\u00a0\u00a0\u00a0\u00a0\u00a0\u00a0\u00a0 : Sangat menarik sekali ya pak, boleh cek perlengkapannya\npak?</span></span>\n<span>\n<span>Penjual\u00a0\u00a0\u00a0\u00a0\u00a0\u00a0\u00a0\u00a0\u00a0\u00a0\u00a0\u00a0\u00a0\u00a0\u00a0\u00a0\u00a0\u00a0\u00a0\u00a0\u00a0\u00a0\u00a0 : oh ya , silahkan. </span></span>\n<span>\n<span>Pembeli\u00a0\u00a0\u00a0\u00a0\u00a0\u00a0\u00a0\u00a0\u00a0\u00a0 : Terimakasih pak. ( Langsung mengecek mobil tersebut )</span></span>\n<span>\n<span>Penjual\u00a0\u00a0\u00a0\u00a0\u00a0\u00a0\u00a0\u00a0\u00a0\u00a0\u00a0\u00a0\u00a0\u00a0\u00a0\u00a0\u00a0\u00a0\u00a0\u00a0\u00a0\u00a0\u00a0 : ( setelah sdr, Midun selesai mengecek mobil\ntersebut ). Bagaimana ??<br>\nmasih mulus bukan? ( sambil tersenyum )</span></span>\n<span>\n<span>Pembeli\u00a0\u00a0\u00a0\u00a0\u00a0\u00a0\u00a0\u00a0\u00a0\u00a0 : iya pak, bicara mengenai barang kan suadah jelas ni pak,\nbagaimana kalau harga yang bapak tawarkan??</span></span>\n<span>\n<span>Penjual\u00a0\u00a0\u00a0\u00a0\u00a0\u00a0\u00a0\u00a0\u00a0\u00a0\u00a0\u00a0\u00a0\u00a0\u00a0\u00a0\u00a0\u00a0\u00a0\u00a0\u00a0\u00a0\u00a0 : Nah, untuk masalah harga, setelah saya cari\ninformasi dari berbagai sumber mengenai harga mobil produksi tahun 2006, saya\nmematok harga Rp 225.000.000,00 Nego.</span></span>\n<span>\n<span>Pembeli\u00a0\u00a0\u00a0\u00a0\u00a0\u00a0\u00a0\u00a0\u00a0\u00a0 : Waaah, cukup tinggi ya pak harga nya,,</span></span>\n<span>\n<span>Penjual\u00a0\u00a0\u00a0\u00a0\u00a0\u00a0\u00a0\u00a0\u00a0\u00a0\u00a0\u00a0\u00a0\u00a0\u00a0\u00a0\u00a0\u00a0\u00a0\u00a0\u00a0\u00a0\u00a0 : iya itu sesuai dengan keadaan mobilnya. Dan\nitu kan harga dari bapak, sekarang berapa tawaran dari sdr, Midun.</span></span>\n<span>\n<span>Pembeli\u00a0\u00a0\u00a0\u00a0\u00a0\u00a0\u00a0\u00a0\u00a0\u00a0 : Sebenarnya saya hanya punya anggaran sekitar 200jt pak,\nitupun tidak cash hari ini.</span></span>\n<span>\n<span>Penjual\u00a0\u00a0\u00a0\u00a0\u00a0\u00a0\u00a0\u00a0\u00a0\u00a0\u00a0\u00a0\u00a0\u00a0\u00a0\u00a0\u00a0\u00a0\u00a0\u00a0\u00a0\u00a0\u00a0 : masalah cash itu tidak usah terlalu\ndipikirkan sdr. Midun. Jika kesepakatan harga sesuai, bapak bisa memberi waktu\nuntuk pelunasannya. Sekarang berapa penawaran sdr. Midun.</span></span>\n<span>\n<span>Pembeli\u00a0\u00a0\u00a0\u00a0\u00a0\u00a0\u00a0\u00a0\u00a0\u00a0 : Kalau saya menawar, giman kalau 18ojt pak?</span></span>\n<span>\n<span>Penjual\u00a0\u00a0\u00a0\u00a0\u00a0\u00a0\u00a0\u00a0\u00a0\u00a0\u00a0\u00a0\u00a0\u00a0\u00a0\u00a0\u00a0\u00a0\u00a0\u00a0\u00a0\u00a0\u00a0 : Waahh, itu terlalu jauh sdr. Midun. Sdr kan\nsudah tahu kondisi mobil ini. Jadi bapak rasa harga yang bapak tawarkan sesuai\ndengan keadaan mobilnya, dan tawaran sdr. Midun jauh dibawah harga standarnya.</span></span>\n<span>\n<span>Pembeli\u00a0\u00a0\u00a0\u00a0\u00a0\u00a0\u00a0\u00a0\u00a0\u00a0 : jika dilihat dari keadaan mobil, betul si pak, keadaan\nnya masih bagus, tapi anggaran saya Cuma segitu tadi pak, giman kalau saya\nnaikkan 1 juta pak?</span></span>\n<span>\n<span>Penjual\u00a0\u00a0\u00a0\u00a0\u00a0\u00a0\u00a0\u00a0\u00a0\u00a0\u00a0\u00a0\u00a0\u00a0\u00a0\u00a0\u00a0\u00a0\u00a0\u00a0\u00a0\u00a0\u00a0 : Kalau segitu , belum bisa bapak melepas\nmobil ini. Gimana kalau bapak beri pilihan, kalau sdr. Midun benar-benar\nmenginginkan mobil ini, bapak bisa mengasih waktu 1 bulan tuk sdr. melunasi\nsisa dari harga anggaran sdr. yaitu 25 juta lagi. Bagaimana sdr. Midun?</span></span>\n<span>\n<span>Pembeli\u00a0\u00a0\u00a0\u00a0\u00a0\u00a0\u00a0\u00a0\u00a0\u00a0 : Alternatif yang bagus pak. Sebenarnya saya memang\ntertarik dengan mobil bapak ini. Tapi masalah harga yang belum sesuai. Gimana\nkalau pas dengan harga 200jt pak?</span></span>\n<span>\n<span>Penjual\u00a0\u00a0\u00a0\u00a0\u00a0\u00a0\u00a0\u00a0\u00a0\u00a0\u00a0\u00a0\u00a0\u00a0\u00a0\u00a0\u00a0\u00a0\u00a0\u00a0\u00a0\u00a0\u00a0 :\u00a0\nBaiklah sdr. midun , gimana kalau kita ambil tengahnya, yaitu 215jt, itu\nsudah bapak kurangkan 10jt. Jika masih dibawah dari harga ini, bapak tidak bisa\nmelepas mobil ini. Jadi gimana sdr Midun?</span></span>\n<span>\n<span>Pembeli\u00a0\u00a0\u00a0\u00a0\u00a0\u00a0\u00a0\u00a0\u00a0\u00a0 : Sepertinya harga yang menarik pak, Baiklah pak, tetapi\npembayarannya sesuai dengan alternative bapak tadi, bearti yang 15jt nya akan\nsaya bayar dalam jangka waktu 1 bulan.</span></span>\n<span>\n<span>Penjual\u00a0\u00a0\u00a0\u00a0\u00a0\u00a0\u00a0\u00a0\u00a0\u00a0\u00a0\u00a0\u00a0\u00a0\u00a0\u00a0\u00a0\u00a0\u00a0\u00a0\u00a0\u00a0\u00a0 : Baiklah Sdr. Midun. Jadi pembayarannya\ntunai atau bagaimana?</span></span>\n<span>\n<span>Pembeli\u00a0\u00a0\u00a0\u00a0\u00a0\u00a0\u00a0\u00a0\u00a0\u00a0 : Baiklah pak, pembayarannya separuh tunai disini, dan\nseparuhnya lagi jika mobil telah saya terima ditempat saya, giman pak?</span></span>\n<span>\n<span>Penjual\u00a0\u00a0\u00a0\u00a0\u00a0\u00a0\u00a0\u00a0\u00a0\u00a0\u00a0\u00a0\u00a0\u00a0\u00a0\u00a0\u00a0\u00a0\u00a0\u00a0\u00a0\u00a0\u00a0 : Baiklah sdr. Midun, Silahkan Ttd disini (\nsambil mengajukan surat jual beli ). Terimakasih sdr. Midun, senang bekerja\nsama dengan anda, dan semoga transakasi ini dilakukan dengan ikhlas, dan semoga\nberuntung dengan mobil ini.</span></span>\n<span>\n<span>Pembeli\u00a0\u00a0\u00a0\u00a0\u00a0\u00a0\u00a0\u00a0\u00a0\u00a0 : Terimakasih kembali pak, saya juga merasa senang bekerja\nsama dengan bapak. Baiklah pak, lebih baik saya pulang sekarang, dan saya tunggu\nkedatangan mobil ini, dan ini alamat rumah saya ( sambil menunjukan alamat\nrumah ).</span></span>\n<span>\n<span>Penjual\u00a0\u00a0\u00a0\u00a0\u00a0\u00a0\u00a0\u00a0\u00a0\u00a0\u00a0\u00a0\u00a0\u00a0\u00a0\u00a0\u00a0\u00a0\u00a0\u00a0\u00a0\u00a0\u00a0 : Baiklah sdr. Midun, semoga selamat dijalan.\nDan tunggu saja 2 jam dari sekarang.</span></span>\n<span>\n<span>Pembeli\u00a0\u00a0\u00a0\u00a0\u00a0\u00a0\u00a0\u00a0\u00a0\u00a0 : sekali lagi terimaksih pak, dan selamat siang.</span></span>\n<span>\n<span>Penjual\u00a0\u00a0\u00a0\u00a0\u00a0\u00a0\u00a0\u00a0\u00a0\u00a0\u00a0\u00a0\u00a0\u00a0\u00a0\u00a0\u00a0\u00a0\u00a0\u00a0\u00a0\u00a0\u00a0 : sama \u2013 sama sdr. Midun. Selamat siang.</span></span>\n\n<br><br>",
                    "attachments": []
                }
            ]
        },
        {
            "slug": "apakah-arti-kata-nonhayati-920",
            "question": "Apakah arti kata nonhayati",
            "attachments": [],
            "answers": [
                {
                    "answer": "Nonhayati adalah unsur alam bukan sumber daya alam hayati yang terdapat di dasar laut dan tanah dibawahnya serta ruang air ZEE Indonesia<br>",
                    "attachments": []
                },
                {
                    "answer": "sumber daya alam yg bukan berasal dri benda hidup",
                    "attachments": []
                }
            ]
        },
        {
            "slug": "contoh-paragraf-yang-berupa-kalimat-esai-524",
            "question": "Contoh paragraf yang berupa\u00a0kalimat esai",
            "attachments": [],
            "answers": [
                {
                    "answer": "<span>Paragraf pertamaDalam paragraf ini, penulis memperkenalkan topik yang akan dikemukakan, berikut tesisnya. Tesis ini harus dikemukakan dalam kalimat yang singkat dan jelas, sedapat mungkin pada kalimat pertama. Selanjutnya pembaca diperkenalkan pada tiga paragraf berikutnya yang mengembangkan tesis tersebut dalam beberapa subtopik.Paragraf kedua sampai kelimaKetiga paragraf ini disebut tubuh dari sebuah esai yang memiliki struktur yang sama. Kalimat pendukung tesis dan argumen-argumennya dituliskan sebagai analisis dengan melihat relevansi dan relasinya dengn masing-masing subtopik.Paragraf kelima (terakhir)<span>Pada paragraf kelima merupakan paragraf kesimpulan. Dalam bagian ini, tuliskan kembali tesis dan subtopik yang telah dibahas dalam paragraf kedua sampai kelima sebagai sebuah sintesis untuk meyakinkan pembaca.</span></span>",
                    "attachments": []
                },
                {
                    "answer": "Pendidikan itu merupakan salah satu hak warga negara.Pendidikan mampu mempengaruhi maju atau tidaknya suatu negara.Namun kenyataannya,banyak anak yang tidak mendapat hak ini dikarenakan alasan tertentu.<br>Alasan mereka biasanya tidak punya biaya untuk sekolah,akses menuju sekolah yang sulit,atau bahkan karena sekolahnya itu sendiri yang rusak.Padahal anggaran biaya negara untuk sektor pendidikan cukup besar tapi masih banyak anak di negeri ini yang sulit untuk mendapat pendidikan.<br>Jadi sebagai generasi muda,bagi yang mampu bersekolah kita harus bersyukur karena banyak yang di daerah-daerah tertentu sulit untuk bersekolah meskipun niat mereka sangat besar.",
                    "attachments": []
                }
            ]
        },
        {
            "slug": "bagaimana-cara-membandingkan-teks-negosiasi-dengan-teks-yang-lain-400",
            "question": "Bagaimana cara membandingkan teks negosiasi dengan teks yang lain????? \u00a0",
            "attachments": [],
            "answers": [
                {
                    "answer": "pada teks negosiasi terdapat beberapa pokok-pokok atau struktur yang ada pada teks negosiasi dan adanya hasil kesepakatan<br>",
                    "attachments": []
                },
                {
                    "answer": "Jika teks negoisasi terdapat pokok pokok<br><br>",
                    "attachments": []
                }
            ]
        },
        {
            "slug": "paham-liberalisme-muncul-pertama-kali-di-negara-apa-340",
            "question": "Paham liberalisme muncul pertama kali di negara apa?",
            "attachments": [],
            "answers": [
                {
                    "answer": "<span>Liberalisme pertama kali dikenalkan oleh negara Inggris yang dikaitkan oleh alam pemikiran yang disebut zaman pencerahan atau aukflarung yang menyatakan bahwa manusia memberikan penghargaan dan kepercayaan besar kepada ratio karena ratio dinilai sebagai kekuatan yang menerangi segala sesuatu di dunia ini dan manusia bias banyak berbuat berdasarkan ratio yang dimilikinya. </span><br>",
                    "attachments": []
                },
                {
                    "answer": "menurut saya di prancis,maaf kalau salah <br>",
                    "attachments": []
                }
            ]
        },
        {
            "slug": "contoh-teks-dialog-negosiasi-tentang-pelayanan-publik-656",
            "question": "Contoh teks dialog negosiasi tentang pelayanan publik",
            "attachments": [],
            "answers": [
                {
                    "answer": "<span>Mahasiswa 1: Saya sudah membuat proposal penelitian ini terlebih dahulu pak<br>Mahasiswa\n 2: Tetapi ini adalah ide yang sudah saya rancang sejak awal. Kami \nmemang pernah membicarakannya tapi saya tidak menyangka bahwa ide saya \nini akhirnya disabotase<br>Dosen: Apa tidak sebaiknya kamu memulai \nmenyusun proposal dengan ide yang lain? Karena dia (mahasiswa 1) memang \ntelah menyusun proposal penelitiannya terlebih dahulu, sedangkan kamu \nbelum. Jadi asumsi saya dia yang lebih dulu mengerjakannya dan berhak \natas ide penelitian ini<br>Mahasiswa 2: tapi ini tidak adil bagi saya pak. Saya merasa dirugikan. <br>Mahasiswa 1: Saya mengubah beberapa konsep dalam rancangan penelitian saya pak<br>Mahsiswa\n 2: Tidak bisa semudah itu. Konsep dasar yang sudah saya rumuskan dan \nsaya tunjukkan pada dia semuanya disalin. Sekali lagi ini tidak adil \nbagi saya. Tidak semudah itu memperoleh ide dan menrancangnya dalam \nsebuah kerangka pikir yang utuh. Saya hanya kalah cepat dalam menyusun \nproposal yang harus saya tunjukkan pada anda. Tapi bukan berarti hasil \nkerja keras saya itu bisa diklaim begitu saja. Saya menghendaki adanya \nkompetisi yang sehat pak.<br>Dosen: Begini saja. Saya akan menawarkan \npada kalian, kalian bisa melakukan penelitian dengan pokok masalah yang \nsama tapi dengan lokasi penelitian yang berbeda. Sangat dimungkinkan \nhasil penelitian kalian nantinya pun akan berbeda. Disamping kalian akan\n punya kesempatan untuk membuktikan diri nantinya. Kualitas penelitian \nsiapa yang terbaik diantara kalian. Bagaimana? Apa kalian bersedia?<br>Mahasiswa 2: saya akan buktikan. Saya harus mempertahankan ide saya dan memperjuangkan hak atas gagasan saya itu.<br>Mahasiswa 1: Baiklah, sepertinya tidak ada pilihan lain.</span><br>",
                    "attachments": []
                },
                {
                    "answer": "<span>NEGOSIASI<span>\u00a0KASUS TKI DI LUAR NEGERI</span><br>JAKARTA\u2014Penunjukkan pengacara tetap untuk mengawal proses hukum TKI yang terancam hukuman mati di Malaysia tidak semulus di Arab Saudi. Negosiasi dengan Sebastian Cha, pengacara yang lolos fit and proper tes putus di tengah jalan. Negosiasi deadlock karena urusan nilai kontrak dan mekanisme pembayarannya.Juru bicara Satgas penanganan TKI yang terancam hukuman mati Humphrey Djemat di Jakarta kemarin (19/12) menuturkan, pengacara Sebastian Cha meminta nilai kontrak sebesar 3 juta ringgit atau sekitar Rp9 miliar untuk durasi satu tahun. Kontrak ini untuk menangani 187 kasus hukum yang berujung ancaman hukuman mati untuk TKI. Dalam proses negosiasi, pengacara ternama di negeri Jiran itu juga meminta duit kontrak dibayar dimuka.</span>Terkait urusan harga, Humphrey mengatakan pemerintah melalui satgas menawar menjadi 2,5 juta ringgit atau sekitar Rp7,1 miliar untuk masa kerja satu tahun. \u201cSayangnya Sebastian tidak mau negosiasi. Dia tetap kukuh meminta 3 juta ringgit,\u201d tandasnya. Menurut Humphrey, pemerintah tidak bisa mengabulkan begitu saja nilai kontrak yang ditawarkan oleh pengacara tetap TKI. Sebab, nanti satgas juga akan diaudit. Dia menegaskan, jika mengabulkan penawaran Sebastian itu, satgas akan dicecar pertanyaan auditor; Kenapa kok tidak ditawar? Satgas sempat menaikkan tawarannya, asalkan tidak sampai 3 juta ringgit. Tetapi, Sebastian masih belum goyah dengan harga yang dia pasang tadi.Sementara untuk urusan skema pembayaran duit kontrak, Humphrey mengatakan pemerintah keberatan sekali dengan sistem yang diminta Sebastian. Dia menegaskan, pemerintah atau satgas tidak bisa membayarkan uang kontrak dalam satu tahapan. \u201cMinimal kami bayarkan dalam tiga tahap. Supaya bisa melakukan evaluasi. Jaminannya apa terhadap kinerjanya selama setahu,\u201d kata dia. Humphrey mencontohkan, pembayaran kontrak pengacara TKI paten di Arab Saudi dengan nilai sekitar Rp5 miliar dibayarkan dalam empat tahap.Humphrey mengatakan, negosiasi yang digelar Jumat lalu (16/12) di Kuala Lumpur itu berlangsung alot. Akhirnya, negosiasi deadlock. Dengan terbuka, satgas dan calon pengacara tetap TKI di Malaysia sepakat jika negosiasi dibatalkan. Humphrey mengatakan, terlalu beresiko jika memaksakan negosiasi dengan Sebastian. Dia tidak mau mengambil resiko, apalagi upaya ini berkaitan erat dengan perlindungan TKI di negara serumpun Indonesia itu.Ini artinya, satgas harus berkutat lagi dalam urusan fit and proper tes penjaringan calon pengacara tetap menggantikan Sebastian. Humphrey mengatakan, satgas berharap bulan ini juga sudah ada pendantanganan kontrak penunjukan pengacara tetap untuk TKI di Malaysia. Untuk urusan ini, perwakilan Indonesia di Malaysia akan meminta rekomendasi dari Malaysia Bar Association (asosiasi advokat malaysia) nama-nama pengacara jempolan di Malaysia.<span>Humphrey menegaskan, upaya satgas menangani TKI terancam hukuman mati di Malaysia tidak bisa diartikan kaku harus membebaskan dari hukuman mati. Sebab, katanya, rata-rata TKI yang terancam hukuman mati di Malaysia terlibat sindikat perdagangan narkotika kelas kakap.\u00a0\u00a0 Upaya satgas adalah, untuk memastikan para TKI mendapatkan hak untuk memperoleh pendampingan selama menjalani persidangan. Meskipun begitu, satgas tetap memperioritaskan pembebasan TKI yang terancam dihukum mati karena membela diri. Misalnya, membela diri karena akan diperkosa majikannya. Atau juga membela diri karena terlalu sering dianiaya sang juragan. (wan)</span>",
                    "attachments": []
                }
            ]
        }
    ]
}